Metadata-Version: 2.1
Name: topsis-102003083-Utkarsh
Version: 1.1.0
Summary: A Python package implementing TOPSIS technique.
Home-page: https://github.com/UTK21/topsis-project
Author: Utkarsh Chaudhary
Author-email: ukguy21@gmail.com
License: MIT
Platform: UNKNOWN
Classifier: License :: OSI Approved :: MIT License
Classifier: Programming Language :: Python :: 3
Classifier: Programming Language :: Python :: 3.7
License-File: LICENSE
Requires-Dist: numpy
Requires-Dist: pandas
